[
  {
    "heading": "Man must explore, and this is exploration at its greatest",
    "subHeading": "Problems look mighty small from 150 miles up",
    "postedBy": "Posted on September 24, 2014"
  },
  {
    "heading": "I believe every human has a finite number of heartbeats. I don't intend to waste any of mine.",
    "subHeading": "The dreams of yesterday are the hopes of today and the reality of tomorrow.",
    "postedBy": "Posted on September 18, 2014"
  },
  {
    "heading": "Science has not yet mastered prophecy",
    "subHeading": "We predict too much for the next year and yet far too little for the next ten.",
    "postedBy": "Posted on August 24, 2014"
  },
  {
    "heading": "Failure is not an option",
    "subHeading": "Many say exploration is part of our destiny, but it’s actually our duty to future generations.",
    "postedBy": "Posted on July 8, 2014"
  }
]
